algorithm_x/__init__.py
algorithm_x/tests/__init__.py
algorithm_x/tests/test_basic.py
algorithm_x-0.1.0.dist-info/LICENSE
algorithm_x-0.1.0.dist-info/METADATA
algorithm_x-0.1.0.dist-info/WHEEL
algorithm_x-0.1.0.dist-info/top_level.txt
algorithm_x-0.1.0.dist-info/RECORD
