Metadata-Version: 2.1
Name: algorithm-x
Version: 0.1.0
Summary: An efficient implementation of Algorithm X
Home-page: https://github.com/SuprDewd/algorithm_x_python
Author: Bjarki Ágúst Guðmundsson
Author-email: suprdewd@gmail.com
License: UNKNOWN
Platform: UNKNOWN
Classifier: Development Status :: 2 - Pre-Alpha
Classifier: Programming Language :: Python :: 2
Classifier: Programming Language :: Python :: 3
Classifier: License :: OSI Approved :: MIT License
Classifier: Operating System :: OS Independent
